airplane/__init__.py
airplane/models.py
airplane/pathing.py
airplane/utils.py
airplane/management/__init__.py
airplane/management/commands/__init__.py
airplane/management/commands/aircache.py
airplane/management/commands/airinfo.py
airplane/templatetags/__init__.py
airplane/templatetags/airplanetags.py
airplane/tests/__init__.py
airplane/tests/test_airplane.py
django_airplane-1.1.1.dist-info/LICENSE
django_airplane-1.1.1.dist-info/METADATA
django_airplane-1.1.1.dist-info/WHEEL
django_airplane-1.1.1.dist-info/top_level.txt
django_airplane-1.1.1.dist-info/RECORD
